cybertechmind_cve_2025_55182/__init__.py
cybertechmind_cve_2025_55182/cli.py
cybertechmind_cve_2025_55182/core.py
cybertechmind_cve_2025_55182-1.0.2.dist-info/licenses/LICENSE
cybertechmind_cve_2025_55182-1.0.2.dist-info/METADATA
cybertechmind_cve_2025_55182-1.0.2.dist-info/WHEEL
cybertechmind_cve_2025_55182-1.0.2.dist-info/entry_points.txt
cybertechmind_cve_2025_55182-1.0.2.dist-info/top_level.txt
cybertechmind_cve_2025_55182-1.0.2.dist-info/RECORD
