Metadata-Version: 2.4
Name: CYBERTECHMIND-CVE-2025-55182
Version: 1.0.2
Summary: React2Shell – CVE-2025-55182 Next.js RSC RCE
Author: Moovendhan V
Requires-Python: >=3.8
License-File: LICENSE
Requires-Dist: requests
Dynamic: license-file
